notion_database_bot/__init__.py
notion_database_bot/main.py
notion_database_bot-0.0.5.dist-info/LICENSE
notion_database_bot-0.0.5.dist-info/METADATA
notion_database_bot-0.0.5.dist-info/WHEEL
notion_database_bot-0.0.5.dist-info/top_level.txt
notion_database_bot-0.0.5.dist-info/RECORD
