Metadata-Version: 2.1
Name: notion-database-bot
Version: 0.0.5
Summary: A package for synchronizing data in Notion Database through Notion official api.
Home-page: https://github.com/zhliu0106/Notion-Database-Bot
Author: Oliver Liu
Author-email: zhliu0106@gmail.com
Classifier: Programming Language :: Python :: 3
Classifier: License :: OSI Approved :: MIT License
Classifier: Operating System :: OS Independent
License-File: LICENSE
